pytcl/__init__.py
pytcl/logging_config.py
pytcl/assignment_algorithms/__init__.py
pytcl/assignment_algorithms/data_association.py
pytcl/assignment_algorithms/dijkstra_min_cost.py
pytcl/assignment_algorithms/gating.py
pytcl/assignment_algorithms/jpda.py
pytcl/assignment_algorithms/nd_assignment.py
pytcl/assignment_algorithms/network_flow.py
pytcl/assignment_algorithms/network_simplex.py
pytcl/assignment_algorithms/three_dimensional/__init__.py
pytcl/assignment_algorithms/three_dimensional/assignment.py
pytcl/assignment_algorithms/two_dimensional/__init__.py
pytcl/assignment_algorithms/two_dimensional/assignment.py
pytcl/assignment_algorithms/two_dimensional/kbest.py
pytcl/astronomical/__init__.py
pytcl/astronomical/ephemerides.py
pytcl/astronomical/lambert.py
pytcl/astronomical/orbital_mechanics.py
pytcl/astronomical/reference_frames.py
pytcl/astronomical/relativity.py
pytcl/astronomical/sgp4.py
pytcl/astronomical/special_orbits.py
pytcl/astronomical/time_systems.py
pytcl/astronomical/tle.py
pytcl/atmosphere/__init__.py
pytcl/atmosphere/ionosphere.py
pytcl/atmosphere/models.py
pytcl/atmosphere/nrlmsise00.py
pytcl/clustering/__init__.py
pytcl/clustering/dbscan.py
pytcl/clustering/gaussian_mixture.py
pytcl/clustering/hierarchical.py
pytcl/clustering/kmeans.py
pytcl/containers/__init__.py
pytcl/containers/base.py
pytcl/containers/cluster_set.py
pytcl/containers/covertree.py
pytcl/containers/kd_tree.py
pytcl/containers/measurement_set.py
pytcl/containers/rtree.py
pytcl/containers/track_list.py
pytcl/containers/vptree.py
pytcl/coordinate_systems/__init__.py
pytcl/coordinate_systems/conversions/__init__.py
pytcl/coordinate_systems/conversions/geodetic.py
pytcl/coordinate_systems/conversions/spherical.py
pytcl/coordinate_systems/jacobians/__init__.py
pytcl/coordinate_systems/jacobians/jacobians.py
pytcl/coordinate_systems/projections/__init__.py
pytcl/coordinate_systems/projections/projections.py
pytcl/coordinate_systems/rotations/__init__.py
nrl_tracker-1.11.1.dist-info/LICENSE
nrl_tracker-1.11.1.dist-info/METADATA
nrl_tracker-1.11.1.dist-info/WHEEL
nrl_tracker-1.11.1.dist-info/top_level.txt
nrl_tracker-1.11.1.dist-info/RECORD
