Metadata-Version: 2.1
Name: nrl-tracker
Version: 1.11.1
Summary: Python port of the U.S. Naval Research Laboratory's Tracker Component Library for target tracking algorithms
Author: Original: David F. Crouse, Naval Research Laboratory
Maintainer: Python Port Contributors
Project-URL: Homepage, https://pytcl.readthedocs.io/en
Project-URL: Documentation, https://pytcl.readthedocs.io/en/latest/docs.html
Project-URL: Repository, https://github.com/nedonatelli/TCL
Project-URL: Bug Tracker, https://github.com/nedonatelli/TCL/issues
Project-URL: Original MATLAB Library, https://github.com/USNavalResearchLaboratory/TrackerComponentLibrary
Keywords: tracking,kalman-filter,target-tracking,data-association,estimation,navigation,coordinate-systems,signal-processing
Classifier: Development Status :: 3 - Alpha
Classifier: Intended Audience :: Science/Research
Classifier: Intended Audience :: Developers
Classifier: License :: Public Domain
Classifier: Operating System :: OS Independent
Classifier: Programming Language :: Python :: 3
Classifier: Programming Language :: Python :: 3.10
Classifier: Programming Language :: Python :: 3.11
Classifier: Programming Language :: Python :: 3.12
Classifier: Topic :: Scientific/Engineering
Classifier: Topic :: Scientific/Engineering :: Mathematics
Classifier: Topic :: Scientific/Engineering :: Physics
Classifier: Topic :: Scientific/Engineering :: Astronomy
Requires-Python: >=3.10
License-File: LICENSE
Requires-Dist: numpy>=1.24.0
Requires-Dist: scipy>=1.10.0
Requires-Dist: numba>=0.57.0
Provides-Extra: all
Requires-Dist: nrl-tracker[astronomy,dev,geodesy,optimization,signal,visualization]; extra == "all"
Provides-Extra: astronomy
Requires-Dist: astropy>=5.0; extra == "astronomy"
Requires-Dist: jplephem>=2.18; extra == "astronomy"
Provides-Extra: benchmark
Requires-Dist: pytest-benchmark>=4.0.0; extra == "benchmark"
Provides-Extra: dev
Requires-Dist: pytest>=7.0.0; extra == "dev"
Requires-Dist: pytest-cov>=4.0.0; extra == "dev"
Requires-Dist: pytest-xdist>=3.0.0; extra == "dev"
Requires-Dist: pytest-benchmark>=4.0.0; extra == "dev"
Requires-Dist: pytest-timeout>=2.0.0; extra == "dev"
Requires-Dist: nbval>=0.10.0; extra == "dev"
Requires-Dist: hypothesis>=6.0.0; extra == "dev"
Requires-Dist: black>=23.0.0; extra == "dev"
Requires-Dist: isort>=5.12.0; extra == "dev"
Requires-Dist: flake8>=7.0.0; extra == "dev"
Requires-Dist: mypy>=1.0.0; extra == "dev"
Requires-Dist: pre-commit>=3.0.0; extra == "dev"
Requires-Dist: sphinx>=6.0.0; extra == "dev"
Requires-Dist: sphinx-rtd-theme>=1.2.0; extra == "dev"
Requires-Dist: myst-parser>=1.0.0; extra == "dev"
Requires-Dist: nbsphinx>=0.9.0; extra == "dev"
Requires-Dist: jupyter>=1.0.0; extra == "dev"
Requires-Dist: ipykernel>=6.0.0; extra == "dev"
Provides-Extra: geodesy
Requires-Dist: pyproj>=3.4.0; extra == "geodesy"
Requires-Dist: geographiclib>=2.0; extra == "geodesy"
Provides-Extra: gpu
Requires-Dist: cupy-cuda12x>=12.0.0; extra == "gpu"
Provides-Extra: gpu-apple
Requires-Dist: mlx>=0.5.0; extra == "gpu-apple"
Provides-Extra: optimization
Requires-Dist: cvxpy>=1.3.0; extra == "optimization"
Provides-Extra: signal
Requires-Dist: pywavelets>=1.4.0; extra == "signal"
Provides-Extra: visualization
Requires-Dist: plotly>=5.15.0; extra == "visualization"
